[
  {
    "name": "Pokémon TCG: First Partner Illustration Collection—Series 2",
    "url": "https://a.co/d/07qe93xW",
    "active": true,
    "amazon_only": false,
    "max_price": 600.0
  },
  {
    "name": "Pokémon TCG: Mega Evolution— Ascended Heroes Booster Bundle",
    "url": "https://a.co/d/0bHBZlWY",
    "active": true,
    "amazon_only": false,
    "max_price": 800.0
  },
  {
    "name": "Pokémon TCG: Mega Evolution— Ascended Heroes Elite Trainer Box",
    "url": "https://a.co/d/0i6hSp78",
    "active": true,
    "amazon_only": false,
    "max_price": 1300.0
  },
  {
    "name": "Pokémon TCG Day 2026 Collection",
    "url": "https://a.co/d/0hW77JzQ",
    "active": true,
    "amazon_only": false,
    "max_price": 450.0
  },
  {
    "name": "Pokémon TCG: Mega Evolution—Ascended Heroes - Premium Poster Collection—Mega Lucario, 10 Piezas",
    "url": "https://a.co/d/0bLlISBc",
    "active": true,
    "amazon_only": false,
    "max_price": 1400.0
  },
  {
    "name": "Pokémon TCG: Mega Evolution—Ascended Heroes - Premium Poster Collection—Mega Gardevoir, 10 Piezas",
    "url": "https://a.co/d/0haxH7ni",
    "active": true,
    "amazon_only": false,
    "max_price": 1400.0
  },
  {
    "name": "Pokémon TCG: Mega Evolution—Ascended Heroes First Partners Deluxe Pin Collection (3 Tarjetas Promocionales de Aluminio, 1 Pin de Lujo y 5 Paquetes de Refuerzo",
    "url": "https://a.co/d/08gLVRnj",
    "active": true,
    "amazon_only": true,
    "max_price": 600.0
  },
  {
    "name": "Pokémon TCG: Mega Evolution - Ascended Heroes Collection-Erika (1 Foil Promo Card, 1 Coin & 2 Booster Packs)",
    "url": "https://a.co/d/0eCt7jMN",
    "active": true
  },
  {
    "name": "Pokémon TCG: Mega Evolution—Ascended Heroes Mega Meganium ex Box (1 Foil Promo Card, 1 Oversize Lenticular Card & 4 Booster Packs)",
    "url": "https://a.co/d/09uf971B",
    "active": true,
    "amazon_only": false,
    "max_price": 600.0
  },
  {
    "name": "Pokémon TCG: Mega Evolution—Ascended Heroes Mega Feraligatr ex Box (1 Foil Promo Card, 1 Oversize Lenticular Card & 4 Booster Packs)",
    "url": "https://a.co/d/0eDs8RrT",
    "active": true,
    "amazon_only": false,
    "max_price": 600.0
  },
  {
    "name": "Pokémon TCG: Mega Evolution—Ascended Heroes Mega Emboar ex Box (1 Foil Promo Card, 1 Oversize Lenticular Card & 4 Booster Packs)",
    "url": "https://a.co/d/0hA5JQaR",
    "active": true,
    "amazon_only": false,
    "max_price": 600.0
  },
  {
    "name": "Pokémon TCG: Mega Evolution—Ascended Heroes Tech Sticker Collection - Gastly, 3 Piezas",
    "url": "https://a.co/d/0baINKLH",
    "active": true
  },
  {
    "name": "Pokémon TCG: Mega Evolution—Chaos Rising Booster Bundle",
    "url": "https://a.co/d/05Hx0wXw",
    "active": true,
    "amazon_only": true,
    "max_price": 750.0
  },
  {
    "name": "Pokémon TCG: Mega Evolution—Ascended Heroes Tech Sticker Collection - Charmander",
    "url": "https://a.co/d/0d6TTDCh",
    "active": true,
    "amazon_only": true,
    "max_price": null
  },
  {
    "name": "Pokémon TCG: First Partner Illustration Collection—Series 3",
    "url": "https://a.co/d/04ON1FEM",
    "active": true,
    "amazon_only": false,
    "max_price": 600.0
  },
  {
    "name": "Pokémon TCG: Iono's Bellibolt ex Premium Collection",
    "url": "https://a.co/d/07LJHhFI",
    "active": true
  },
  {
    "name": "Pokémon TCG: Mega Evolution—Chaos Rising Elite Trainer Box, 1 Pieza",
    "url": "https://a.co/d/01Vndz5C",
    "active": true,
    "amazon_only": false,
    "max_price": 1100.0
  },
  {
    "name": "Pokémon TCG: Colección Pokémon Day 2026 (1 Tarjeta Promocional, 1 Moneda y 3 Paquetes de Refuerzo)",
    "url": "https://a.co/d/05qEGStP",
    "active": true,
    "amazon_only": true,
    "max_price": 450.0
  },
  {
    "name": "Pokémon TCG: Mega Evolution—Ascended Heroes - Premium Poster Collection—Mega Gardevoir, 10 Piezas LINK 2",
    "url": "https://a.co/d/05nvUFdi",
    "active": true,
    "amazon_only": true,
    "max_price": 1400.0
  },
  {
    "name": "Pokémon TCG: Mega Evolution—Pitch Black Booster Bundle",
    "url": "https://a.co/d/03KoAURn",
    "active": true,
    "amazon_only": true,
    "max_price": 800.0
  },
  {
    "name": "Pokémon TCG: Mega Charizard Y Tin",
    "url": "https://a.co/d/0a76bOkV",
    "active": true,
    "amazon_only": true,
    "max_price": null
  },
  {
    "name": "Pokémon TCG: Scarlet & Violet—Prismatic Evolutions Booster Bundle",
    "url": "https://a.co/d/0bHYjzk8",
    "active": true,
    "amazon_only": true,
    "max_price": 800.0
  },
  {
    "name": "Pokémon TCG: Mega Evolution 3-Pack Blister - Sneasel LINK 2",
    "url": "https://a.co/d/0a8801VZ",
    "active": true,
    "amazon_only": true,
    "max_price": 400.0
  },
  {
    "name": "Pokémon TCG: Lata Mega Charizard",
    "url": "https://a.co/d/06Ho6JqQ",
    "active": true,
    "amazon_only": true,
    "max_price": null
  },
  {
    "name": "Pokémon TCG: Scarlet & Violet—Prismatic Evolutions Premium Figure Collection",
    "url": "https://a.co/d/08BW6tmt",
    "active": true,
    "amazon_only": true,
    "max_price": null
  },
  {
    "name": "Pokemon TCG Escarlata y Violeta Evoluciones Prismáticas Lucario ex & Tyranitar ex Caja de Colección Premium - 14 Paquetes",
    "url": "https://a.co/d/0aI6pckV",
    "active": true,
    "amazon_only": true,
    "max_price": null
  },
  {
    "name": "Pokémon TCG: Mega Evolution—Pitch Black Elite Trainer Box",
    "url": "https://a.co/d/058om4p2",
    "active": true,
    "amazon_only": true,
    "max_price": 1200.0
  },
  {
    "name": "Pokémon TCG: Mega Evolution—Pitch Black Three-Booster Blister",
    "url": "https://a.co/d/03cDKJgX",
    "active": true,
    "amazon_only": true,
    "max_price": 500.0
  },
  {
    "name": "Pokémon TCG: Scarlet y Violet: Evoluciones prismáticas, blíster de dos sobres",
    "url": "https://a.co/d/034YCxth",
    "active": true,
    "amazon_only": true,
    "max_price": null
  },
  {
    "name": "Pokémon TCG: Mega Evolution—Chaos Rising Build & Battle Box",
    "url": "https://a.co/d/0dVX31g5",
    "active": true,
    "amazon_only": false,
    "max_price": null
  },
  {
    "name": "Pokémon Mega Greninja ex Premium Collection",
    "url": "https://a.co/d/04N15Nkh",
    "active": true,
    "amazon_only": true,
    "max_price": null
  },
  {
    "name": "Pokémon TCG: Mega Evolution—Ascended Heroes First Partners Deluxe Pin Collection (3 Tarjetas Promocionales de Aluminio, 1 Pin de Lujo y 5 Paquetes de Refuerzo",
    "url": "https://www.amazon.com.mx/dp/B0G71VXSWN",
    "max_price": 600.0,
    "amazon_only": true,
    "active": true
  }
]